[
    {
        "identifiers": ["uuid:3022a707-f5b6-4be8-be4e-c1eeb7c1cdec"],
        "name": "Nasdanika",
        "icon": "https://docs.nasdanika.org/images/nasdanika-logo.png",
        "location": "https://www.nasdanika.org",
        "type": {
            "name": "Action",
            "ns-uri": "ecore://nasdanika.org/html/app"
        }
    },
    {
        "container": {
            "reference": "children",
            "identifiers": ["uuid:3022a707-f5b6-4be8-be4e-c1eeb7c1cdec"]
        },
        "identifiers": ["uuid:0161616b-3a75-4493-add8-9a9bfa4d8381"],
        "name": "Search",
        "icon": "fas fa-search",
        "location": "search.html",
        "type": {
            "name": "Action",
            "ns-uri": "ecore://nasdanika.org/html/app"
        }
    },
    {
        "container": {
            "reference": "children",
            "identifiers": ["uuid:3022a707-f5b6-4be8-be4e-c1eeb7c1cdec"]
        },
        "identifiers": ["uuid:f4b69722-9bbb-47ca-8cf2-ca5a9f98522f"],
        "name": "Glossary",
        "icon": "fas fa-book",
        "location": "glossary.html",
        "type": {
            "name": "Action",
            "ns-uri": "ecore://nasdanika.org/html/app"
        }
    },
    {
        "identifiers": ["http://www.eclipse.org/emf/2002/Ecore"],
        "name": "Ecore",
        "icon": "https://cdn.jsdelivr.net/gh/Nasdanika/html@master/ecore.gen/icons/EPackage.gif",
        "location": "index.html",
        "type": {
            "name": "EPackage",
            "ns-uri": "http://www.eclipse.org/emf/2002/Ecore"
        }
    },
    {
        "container": {
            "reference": "eClassifiers",
            "identifiers": ["http://www.eclipse.org/emf/2002/Ecore"]
        },
        "identifiers": ["http://www.eclipse.org/emf/2002/Ecore/eClassifiers/EModelElement"],
        "name": "EModelElement",
        "icon": "https://cdn.jsdelivr.net/gh/Nasdanika/html@master/ecore.gen/icons/EClass.gif",
        "location": "eClassifiers/EModelElement/index.html",
        "type": {
            "name": "EClass",
            "ns-uri": "http://www.eclipse.org/emf/2002/Ecore"
        }
    },
    {
        "container": {
            "reference": "eClassifiers",
            "identifiers": ["http://www.eclipse.org/emf/2002/Ecore"]
        },
        "identifiers": ["http://www.eclipse.org/emf/2002/Ecore/eClassifiers/EPackage"],
        "name": "EPackage",
        "icon": "https://cdn.jsdelivr.net/gh/Nasdanika/html@master/ecore.gen/icons/EClass.gif",
        "location": "eClassifiers/EPackage/index.html",
        "type": {
            "name": "EClass",
            "ns-uri": "http://www.eclipse.org/emf/2002/Ecore"
        }
    },
    {
        "container": {
            "reference": "eClassifiers",
            "identifiers": ["http://www.eclipse.org/emf/2002/Ecore"]
        },
        "identifiers": ["http://www.eclipse.org/emf/2002/Ecore/eClassifiers/EFactory"],
        "name": "EFactory",
        "icon": "https://cdn.jsdelivr.net/gh/Nasdanika/html@master/ecore.gen/icons/EClass.gif",
        "location": "eClassifiers/EFactory/index.html",
        "type": {
            "name": "EClass",
            "ns-uri": "http://www.eclipse.org/emf/2002/Ecore"
        }
    },
    {
        "container": {
            "reference": "eClassifiers",
            "identifiers": ["http://www.eclipse.org/emf/2002/Ecore"]
        },
        "identifiers": ["http://www.eclipse.org/emf/2002/Ecore/eClassifiers/EEnumLiteral"],
        "name": "EEnumLiteral",
        "icon": "https://cdn.jsdelivr.net/gh/Nasdanika/html@master/ecore.gen/icons/EClass.gif",
        "location": "eClassifiers/EEnumLiteral/index.html",
        "type": {
            "name": "EClass",
            "ns-uri": "http://www.eclipse.org/emf/2002/Ecore"
        }
    },
    {
        "container": {
            "reference": "eClassifiers",
            "identifiers": ["http://www.eclipse.org/emf/2002/Ecore"]
        },
        "identifiers": ["http://www.eclipse.org/emf/2002/Ecore/eClassifiers/ENamedElement"],
        "name": "ENamedElement",
        "icon": "https://cdn.jsdelivr.net/gh/Nasdanika/html@master/ecore.gen/icons/EClass.gif",
        "location": "eClassifiers/ENamedElement/index.html",
        "type": {
            "name": "EClass",
            "ns-uri": "http://www.eclipse.org/emf/2002/Ecore"
        }
    },
    {
        "container": {
            "reference": "eClassifiers",
            "identifiers": ["http://www.eclipse.org/emf/2002/Ecore"]
        },
        "identifiers": ["http://www.eclipse.org/emf/2002/Ecore/eClassifiers/EOperation"],
        "name": "EOperation",
        "icon": "https://cdn.jsdelivr.net/gh/Nasdanika/html@master/ecore.gen/icons/EClass.gif",
        "location": "eClassifiers/EOperation/index.html",
        "type": {
            "name": "EClass",
            "ns-uri": "http://www.eclipse.org/emf/2002/Ecore"
        }
    },
    {
        "container": {
            "reference": "eClassifiers",
            "identifiers": ["http://www.eclipse.org/emf/2002/Ecore"]
        },
        "identifiers": ["http://www.eclipse.org/emf/2002/Ecore/eClassifiers/EReference"],
        "name": "EReference",
        "icon": "https://cdn.jsdelivr.net/gh/Nasdanika/html@master/ecore.gen/icons/EClass.gif",
        "location": "eClassifiers/EReference/index.html",
        "type": {
            "name": "EClass",
            "ns-uri": "http://www.eclipse.org/emf/2002/Ecore"
        }
    },
    {
        "container": {
            "reference": "eClassifiers",
            "identifiers": ["http://www.eclipse.org/emf/2002/Ecore"]
        },
        "identifiers": ["http://www.eclipse.org/emf/2002/Ecore/eClassifiers/EGenericType"],
        "name": "EGenericType",
        "icon": "https://cdn.jsdelivr.net/gh/Nasdanika/html@master/ecore.gen/icons/EClass.gif",
        "location": "eClassifiers/EGenericType/index.html",
        "type": {
            "name": "EClass",
            "ns-uri": "http://www.eclipse.org/emf/2002/Ecore"
        }
    },
    {
        "container": {
            "reference": "eClassifiers",
            "identifiers": ["http://www.eclipse.org/emf/2002/Ecore"]
        },
        "identifiers": ["http://www.eclipse.org/emf/2002/Ecore/eClassifiers/EDataType"],
        "name": "EDataType",
        "icon": "https://cdn.jsdelivr.net/gh/Nasdanika/html@master/ecore.gen/icons/EClass.gif",
        "location": "eClassifiers/EDataType/index.html",
        "type": {
            "name": "EClass",
            "ns-uri": "http://www.eclipse.org/emf/2002/Ecore"
        }
    },
    {
        "container": {
            "reference": "eClassifiers",
            "identifiers": ["http://www.eclipse.org/emf/2002/Ecore"]
        },
        "identifiers": ["http://www.eclipse.org/emf/2002/Ecore/eClassifiers/EEnum"],
        "name": "EEnum",
        "icon": "https://cdn.jsdelivr.net/gh/Nasdanika/html@master/ecore.gen/icons/EClass.gif",
        "location": "eClassifiers/EEnum/index.html",
        "type": {
            "name": "EClass",
            "ns-uri": "http://www.eclipse.org/emf/2002/Ecore"
        }
    },
    {
        "container": {
            "reference": "eClassifiers",
            "identifiers": ["http://www.eclipse.org/emf/2002/Ecore"]
        },
        "identifiers": ["http://www.eclipse.org/emf/2002/Ecore/eClassifiers/EParameter"],
        "name": "EParameter",
        "icon": "https://cdn.jsdelivr.net/gh/Nasdanika/html@master/ecore.gen/icons/EClass.gif",
        "location": "eClassifiers/EParameter/index.html",
        "type": {
            "name": "EClass",
            "ns-uri": "http://www.eclipse.org/emf/2002/Ecore"
        }
    },
    {
        "container": {
            "reference": "eClassifiers",
            "identifiers": ["http://www.eclipse.org/emf/2002/Ecore"]
        },
        "identifiers": ["http://www.eclipse.org/emf/2002/Ecore/eClassifiers/ETypedElement"],
        "name": "ETypedElement",
        "icon": "https://cdn.jsdelivr.net/gh/Nasdanika/html@master/ecore.gen/icons/EClass.gif",
        "location": "eClassifiers/ETypedElement/index.html",
        "type": {
            "name": "EClass",
            "ns-uri": "http://www.eclipse.org/emf/2002/Ecore"
        }
    },
    {
        "container": {
            "reference": "eClassifiers",
            "identifiers": ["http://www.eclipse.org/emf/2002/Ecore"]
        },
        "identifiers": ["http://www.eclipse.org/emf/2002/Ecore/eClassifiers/EAnnotation"],
        "name": "EAnnotation",
        "icon": "https://cdn.jsdelivr.net/gh/Nasdanika/html@master/ecore.gen/icons/EClass.gif",
        "location": "eClassifiers/EAnnotation/index.html",
        "type": {
            "name": "EClass",
            "ns-uri": "http://www.eclipse.org/emf/2002/Ecore"
        }
    },
    {
        "container": {
            "reference": "eClassifiers",
            "identifiers": ["http://www.eclipse.org/emf/2002/Ecore"]
        },
        "identifiers": ["http://www.eclipse.org/emf/2002/Ecore/eClassifiers/EStructuralFeature"],
        "name": "EStructuralFeature",
        "icon": "https://cdn.jsdelivr.net/gh/Nasdanika/html@master/ecore.gen/icons/EClass.gif",
        "location": "eClassifiers/EStructuralFeature/index.html",
        "type": {
            "name": "EClass",
            "ns-uri": "http://www.eclipse.org/emf/2002/Ecore"
        }
    },
    {
        "container": {
            "reference": "eClassifiers",
            "identifiers": ["http://www.eclipse.org/emf/2002/Ecore"]
        },
        "identifiers": ["http://www.eclipse.org/emf/2002/Ecore/eClassifiers/EStringToStringMapEntry"],
        "name": "EStringToStringMapEntry",
        "icon": "https://cdn.jsdelivr.net/gh/Nasdanika/html@master/ecore.gen/icons/EClass.gif",
        "location": "eClassifiers/EStringToStringMapEntry/index.html",
        "type": {
            "name": "EClass",
            "ns-uri": "http://www.eclipse.org/emf/2002/Ecore"
        }
    },
    {
        "container": {
            "reference": "eClassifiers",
            "identifiers": ["http://www.eclipse.org/emf/2002/Ecore"]
        },
        "identifiers": ["http://www.eclipse.org/emf/2002/Ecore/eClassifiers/ETypeParameter"],
        "name": "ETypeParameter",
        "icon": "https://cdn.jsdelivr.net/gh/Nasdanika/html@master/ecore.gen/icons/EClass.gif",
        "location": "eClassifiers/ETypeParameter/index.html",
        "type": {
            "name": "EClass",
            "ns-uri": "http://www.eclipse.org/emf/2002/Ecore"
        }
    },
    {
        "container": {
            "reference": "eClassifiers",
            "identifiers": ["http://www.eclipse.org/emf/2002/Ecore"]
        },
        "identifiers": ["http://www.eclipse.org/emf/2002/Ecore/eClassifiers/EClassifier"],
        "name": "EClassifier",
        "icon": "https://cdn.jsdelivr.net/gh/Nasdanika/html@master/ecore.gen/icons/EClass.gif",
        "location": "eClassifiers/EClassifier/index.html",
        "type": {
            "name": "EClass",
            "ns-uri": "http://www.eclipse.org/emf/2002/Ecore"
        }
    },
    {
        "container": {
            "reference": "eClassifiers",
            "identifiers": ["http://www.eclipse.org/emf/2002/Ecore"]
        },
        "identifiers": ["http://www.eclipse.org/emf/2002/Ecore/eClassifiers/EClass"],
        "name": "EClass",
        "icon": "https://cdn.jsdelivr.net/gh/Nasdanika/html@master/ecore.gen/icons/EClass.gif",
        "description": "purum",
        "location": "eClassifiers/EClass/index.html",
        "type": {
            "name": "EClass",
            "ns-uri": "http://www.eclipse.org/emf/2002/Ecore"
        }
    },
    {
        "container": {
            "reference": "eClassifiers",
            "identifiers": ["http://www.eclipse.org/emf/2002/Ecore"]
        },
        "identifiers": ["http://www.eclipse.org/emf/2002/Ecore/eClassifiers/EAttribute"],
        "name": "EAttribute",
        "icon": "https://cdn.jsdelivr.net/gh/Nasdanika/html@master/ecore.gen/icons/EClass.gif",
        "location": "eClassifiers/EAttribute/index.html",
        "type": {
            "name": "EClass",
            "ns-uri": "http://www.eclipse.org/emf/2002/Ecore"
        }
    },
    {
        "container": {
            "reference": "eClassifiers",
            "identifiers": ["http://www.eclipse.org/emf/2002/Ecore"]
        },
        "identifiers": ["http://www.eclipse.org/emf/2002/Ecore/eClassifiers/EObject"],
        "name": "EObject",
        "icon": "https://cdn.jsdelivr.net/gh/Nasdanika/html@master/ecore.gen/icons/EClass.gif",
        "location": "eClassifiers/EObject/index.html",
        "type": {
            "name": "EClass",
            "ns-uri": "http://www.eclipse.org/emf/2002/Ecore"
        }
    }
]